SerenityKaifazheZhinanZhongwenban/README.md
SerenityKaifazheZhinanZhongwenban/__init__.py
SerenityKaifazheZhinanZhongwenban/__main__.py
SerenityKaifazheZhinanZhongwenban/file.epub
SerenityKaifazheZhinanZhongwenban/index.html
SerenityKaifazheZhinanZhongwenban/css/__init__.py
SerenityKaifazheZhinanZhongwenban/css/annotations.css
SerenityKaifazheZhinanZhongwenban/css/main.css
SerenityKaifazheZhinanZhongwenban/css/normalize.css
SerenityKaifazheZhinanZhongwenban/css/popup.css
SerenityKaifazheZhinanZhongwenban/font/__init__.py
SerenityKaifazheZhinanZhongwenban/font/fontello.eot
SerenityKaifazheZhinanZhongwenban/font/fontello.svg
SerenityKaifazheZhinanZhongwenban/font/fontello.ttf
SerenityKaifazheZhinanZhongwenban/font/fontello.woff
SerenityKaifazheZhinanZhongwenban/img/__init__.py
SerenityKaifazheZhinanZhongwenban/img/annotator-glyph-sprite.png
SerenityKaifazheZhinanZhongwenban/img/annotator-icon-sprite.png
SerenityKaifazheZhinanZhongwenban/img/apple-touch-icon.png
SerenityKaifazheZhinanZhongwenban/img/cancelfullscreen.png
SerenityKaifazheZhinanZhongwenban/img/close.png
SerenityKaifazheZhinanZhongwenban/img/fullscreen.png
SerenityKaifazheZhinanZhongwenban/img/loader.gif
SerenityKaifazheZhinanZhongwenban/img/menu-icon.png
SerenityKaifazheZhinanZhongwenban/img/save.png
SerenityKaifazheZhinanZhongwenban/img/saved.png
SerenityKaifazheZhinanZhongwenban/img/settings-s.png
SerenityKaifazheZhinanZhongwenban/img/settings.png
SerenityKaifazheZhinanZhongwenban/img/star.png
SerenityKaifazheZhinanZhongwenban/js/__init__.py
SerenityKaifazheZhinanZhongwenban/js/epub.js
SerenityKaifazheZhinanZhongwenban/js/epub.min.js
SerenityKaifazheZhinanZhongwenban/js/epub.min.map
SerenityKaifazheZhinanZhongwenban/js/hooks.min.js
SerenityKaifazheZhinanZhongwenban/js/hooks.min.map
SerenityKaifazheZhinanZhongwenban/js/reader.js
SerenityKaifazheZhinanZhongwenban/js/reader.js.map
SerenityKaifazheZhinanZhongwenban/js/reader.min.js
SerenityKaifazheZhinanZhongwenban/js/reader.min.map
serenity_kaifazhe_zhinan_zhongwenban-2024.3.3.0.dist-info/METADATA
serenity_kaifazhe_zhinan_zhongwenban-2024.3.3.0.dist-info/WHEEL
serenity_kaifazhe_zhinan_zhongwenban-2024.3.3.0.dist-info/entry_points.txt
serenity_kaifazhe_zhinan_zhongwenban-2024.3.3.0.dist-info/top_level.txt
serenity_kaifazhe_zhinan_zhongwenban-2024.3.3.0.dist-info/RECORD
